qn/__init__.py
qn/diskIO.py
qn/legacy.py
qn/qn.py
qn/test.py
qn/viz.py
qn/configs/__init__.py
qn/configs/default.example.py
qn/configs/default.py
qn/configs/default_load.py
qn-0.2.7.dist-info/licenses/LICENSE
qn-0.2.7.dist-info/METADATA
qn-0.2.7.dist-info/WHEEL
qn-0.2.7.dist-info/top_level.txt
qn-0.2.7.dist-info/RECORD
