Metadata-Version: 2.4
Name: qn
Version: 0.2.7
Summary: Handy functions I use everyday.
Home-page: https://github.com/frlender/qn
Author: Qiaonan Duan
Author-email: geonann@gmail.com
License: MIT
License-File: LICENSE
Requires-Dist: matplotlib
Requires-Dist: seaborn
Requires-Dist: numpy
Requires-Dist: scipy
Requires-Dist: pandas
Requires-Dist: PyYAML
Requires-Dist: scikit-learn
Requires-Dist: dill
Dynamic: author
Dynamic: author-email
Dynamic: home-page
Dynamic: license
Dynamic: license-file
Dynamic: requires-dist
Dynamic: summary
